icspylab/__init__.py
icspylab/ics.py
icspylab/plot.py
icspylab/scatter.py
icspylab/utils.py
tests/__init__.py
tests/conftest.py
tests/settings.py
tests/utils.py
tests/comparisons/__init__.py
tests/comparisons/test_near_rank_deficient.py
tests/comparisons/test_python_ICS_numerical_stability.py
tests/comparisons/test_python_vs_r.py
tests/fixtures/__init__.py
tests/fixtures/fixtures.py
tests/unit/__init__.py
tests/unit/test_ics.py
tests/unit/test_plot.py
tests/unit/test_scatter.py
tests/unit/test_utils.py
icspylab-0.1.0.dist-info/LICENSE.txt
icspylab-0.1.0.dist-info/METADATA
icspylab-0.1.0.dist-info/WHEEL
icspylab-0.1.0.dist-info/top_level.txt
icspylab-0.1.0.dist-info/RECORD
