Metadata-Version: 2.1
Name: icspylab
Version: 0.1.0
Summary: Invariant Coordinate Selection (ICS) for multivariate data analysis.
Home-page: https://github.com/cbecquart/ICSpyLab
Author: Colombe Becquart, Abdallah Abdelsameia
Author-email: colombe.becquart@tse-fr.eu, aabdelsameia1@gmail.com
Maintainer: Colombe Becquart
Maintainer-email: colombe.becquart@tse-fr.eu
Classifier: Programming Language :: Python :: 3
Classifier: License :: OSI Approved :: MIT License
Classifier: Operating System :: OS Independent
Requires-Python: >=3.9
License-File: LICENSE.txt
Requires-Dist: numpy
Requires-Dist: pandas
Requires-Dist: scikit-learn
Requires-Dist: scipy
Requires-Dist: seaborn
Requires-Dist: matplotlib
